crusher/__init__.py
crusher/crusher.py
crusher-0.1.2.dist-info/entry_points.txt
crusher-0.1.2.dist-info/LICENSE
crusher-0.1.2.dist-info/WHEEL
crusher-0.1.2.dist-info/METADATA
crusher-0.1.2.dist-info/RECORD
