Metadata-Version: 2.1
Name: crusher
Version: 0.1.2
Summary: Crush a deeply nested JSON string.
License: MIT
Author: rednafi
Author-email: redowan.nafi@gmail.com
Requires-Python: >=3.7,<4.0
Classifier: License :: OSI Approved :: MIT License
Classifier: Programming Language :: Python :: 3
Classifier: Programming Language :: Python :: 3.7
Classifier: Programming Language :: Python :: 3.8
Classifier: Programming Language :: Python :: 3.9
Requires-Dist: rich (>=10.3.0,<11.0.0)
